turkishpythonV3/__init__.py
turkishpythonV3/core.py
turkishpythonv3-0.3.0.dist-info/METADATA
turkishpythonv3-0.3.0.dist-info/WHEEL
turkishpythonv3-0.3.0.dist-info/top_level.txt
turkishpythonv3-0.3.0.dist-info/RECORD
