Metadata-Version: 2.4
Name: turkishpythonV3
Version: 0.3.0
Summary: Python'u Türkçe yazmak için kütüphane
Author-email: turkishpython <example@mail.com>
License: MIT
Requires-Python: >=3.8
